setup.cfg
setup.py
uitdatabank/__init__.py
uitdatabank/event.py
uitdatabank/searchresults.py
uitdatabank/shortcuts.py
uitdatabank/uitdatabank.py
uitdatabank.egg-info/PKG-INFO
uitdatabank.egg-info/SOURCES.txt
uitdatabank.egg-info/dependency_links.txt
uitdatabank.egg-info/not-zip-safe
uitdatabank.egg-info/requires.txt
uitdatabank.egg-info/top_level.txt